ndsb/__init__.py
ndsb-2.0.0.dist-info/LICENSE
ndsb-2.0.0.dist-info/METADATA
ndsb-2.0.0.dist-info/WHEEL
ndsb-2.0.0.dist-info/top_level.txt
ndsb-2.0.0.dist-info/RECORD
